ppg_pre/__init__.py
ppg_pre/preprocess.py
ppg_pre/utils.py
ppg_pre/sample/ppg0.csv
ppg_pre/sample/ppg1.csv
ppg_pre/sample/ppg2.csv
tests/__init__.py
tests/test_module.py
ppg_pre-0.1.3.dist-info/LICENSE
ppg_pre-0.1.3.dist-info/METADATA
ppg_pre-0.1.3.dist-info/WHEEL
ppg_pre-0.1.3.dist-info/top_level.txt
ppg_pre-0.1.3.dist-info/RECORD
